[
  {
    "id": 1701179229,
    "First name": "nagy",
    "Last name": "mostafa",
    "Email": "nagy@gmail.com",
    "Password": "123",
    "Mobilephone": 1124013355
  },
  {
    "id": 1701261945,
    "First name": "mostafa",
    "Last name": "hussen",
    "Email": "mostafa@gmail.com",
    "Password": "012345",
    "Mobilephone": 1119909294
  },
  {
    "id": 1701648353,
    "First name": "alaa",
    "Last name": "alaa",
    "Email": "alaa@gmail.com",
    "Password": "123",
    "Mobilephone": 1124013355
  },
  {
    "id": 1701724602,
    "First name": "mohamed",
    "Last name": "ahmed",
    "Email": "mohamed@gmail.com",
    "Password": "123456",
    "Mobilephone": 1124013352
  },
  {
    "id": 1701724732,
    "First name": "ahmed",
    "Last name": "mohamed",
    "Email": "ahmed@gmail.com",
    "Password": "12345",
    "Mobilephone": 1124013366
  },
  {
    "id": 1701792360,
    "First name": "nagy",
    "Last name": "mostaf",
    "Email": "nagy@gmail.com",
    "Password": "12345",
    "Mobilephone": 1124013355
  },
  {
    "id": 1705084967,
    "First name": "nagy",
    "Last name": "mostafa",
    "Email": "nagy@gmail.com",
    "Password": "123456",
    "Mobilephone": 1124013346
  }
]